nvidia/__init__.py
nvidia/cuda_cupti/__init__.py
nvidia/cuda_cupti/bin/__init__.py
nvidia/cuda_cupti/bin/checkpoint.dll
nvidia/cuda_cupti/bin/cupti64_2025.2.0.dll
nvidia/cuda_cupti/bin/nvperf_host.dll
nvidia/cuda_cupti/bin/nvperf_target.dll
nvidia/cuda_cupti/bin/pcsamplingutil.dll
nvidia/cuda_cupti/include/__init__.py
nvidia/cuda_cupti/include/cuda_stdint.h
nvidia/cuda_cupti/include/cupti.h
nvidia/cuda_cupti/include/cupti_activity.h
nvidia/cuda_cupti/include/cupti_activity_deprecated.h
nvidia/cuda_cupti/include/cupti_callbacks.h
nvidia/cuda_cupti/include/cupti_checkpoint.h
nvidia/cuda_cupti/include/cupti_common.h
nvidia/cuda_cupti/include/cupti_driver_cbid.h
nvidia/cuda_cupti/include/cupti_events.h
nvidia/cuda_cupti/include/cupti_metrics.h
nvidia/cuda_cupti/include/cupti_nvtx_cbid.h
nvidia/cuda_cupti/include/cupti_pcsampling.h
nvidia/cuda_cupti/include/cupti_pcsampling_util.h
nvidia/cuda_cupti/include/cupti_pmsampling.h
nvidia/cuda_cupti/include/cupti_profiler_host.h
nvidia/cuda_cupti/include/cupti_profiler_target.h
nvidia/cuda_cupti/include/cupti_range_profiler.h
nvidia/cuda_cupti/include/cupti_result.h
nvidia/cuda_cupti/include/cupti_runtime_cbid.h
nvidia/cuda_cupti/include/cupti_sass_metrics.h
nvidia/cuda_cupti/include/cupti_target.h
nvidia/cuda_cupti/include/cupti_version.h
nvidia/cuda_cupti/include/generated_cudaD3D10_meta.h
nvidia/cuda_cupti/include/generated_cudaD3D11_meta.h
nvidia/cuda_cupti/include/generated_cudaD3D9_meta.h
nvidia/cuda_cupti/include/generated_cudaGL_meta.h
nvidia/cuda_cupti/include/generated_cuda_d3d10_interop_meta.h
nvidia/cuda_cupti/include/generated_cuda_d3d11_interop_meta.h
nvidia/cuda_cupti/include/generated_cuda_d3d9_interop_meta.h
nvidia/cuda_cupti/include/generated_cuda_gl_interop_meta.h
nvidia/cuda_cupti/include/generated_cuda_meta.h
nvidia/cuda_cupti/include/generated_cuda_runtime_api_meta.h
nvidia/cuda_cupti/include/generated_cudart_removed_meta.h
nvidia/cuda_cupti/include/generated_nvtx_meta.h
nvidia_cuda_cupti_cu12-12.9.19.dist-info/License.txt
nvidia_cuda_cupti_cu12-12.9.19.dist-info/METADATA
nvidia_cuda_cupti_cu12-12.9.19.dist-info/WHEEL
nvidia_cuda_cupti_cu12-12.9.19.dist-info/top_level.txt
nvidia_cuda_cupti_cu12-12.9.19.dist-info/RECORD
